LICENSE.txt
MANIFEST.in
README.rst
requirements.txt
setup.cfg
setup.py
doc/Makefile
doc/conf.py
doc/index.rst
doc/objects.inv
doc/rst/install.rst
doc/rst/module.rst
doc/rst/refman.rst
doc/rst/tutor.rst
doc/rst/install/libraries.rst
doc/rst/install/lib/network.rst
doc/rst/module/libraries.rst
doc/rst/module/lib/network/dbi.rst
doc/rst/module/lib/network/dbo.rst
doc/rst/module/lib/network/email.rst
doc/rst/module/lib/network/ftp.rst
doc/rst/module/lib/network/inet.rst
doc/rst/module/lib/network/java.rst
doc/rst/module/lib/network/jms.rst
doc/rst/module/lib/network/ldap.rst
doc/rst/module/lib/network/loader.rst
doc/rst/module/lib/network/network.rst
doc/rst/module/lib/network/rest.rst
doc/rst/module/lib/network/rpc.rst
doc/rst/module/lib/network/selen.rst
doc/rst/module/lib/network/soap.rst
doc/rst/module/lib/network/term.rst
doc/rst/module/lib/network/xml.rst
doc/rst/refman/lib/network.rst
doc/rst/tutor/libraries.rst
doc/rst/tutor/lib/network/network.rst
doc/rst/tutor/lib/network/tut10_selen.rst
doc/rst/tutor/lib/network/tut11_soap.rst
doc/rst/tutor/lib/network/tut12_term.rst
doc/rst/tutor/lib/network/tut1_dbi.rst
doc/rst/tutor/lib/network/tut2_email.rst
doc/rst/tutor/lib/network/tut3_ftp.rst
doc/rst/tutor/lib/network/tut4_inet.rst
doc/rst/tutor/lib/network/tut5_java.rst
doc/rst/tutor/lib/network/tut6_jms.rst
doc/rst/tutor/lib/network/tut7_ldap.rst
doc/rst/tutor/lib/network/tut8_rest.rst
doc/rst/tutor/lib/network/tut9_rpc.rst
src/hydratk/__init__.py
src/hydratk/lib/__init__.py
src/hydratk/lib/bridge/__init__.py
src/hydratk/lib/bridge/java.py
src/hydratk/lib/bridge/selen.py
src/hydratk/lib/data/__init__.py
src/hydratk/lib/data/loader.py
src/hydratk/lib/data/xml.py
src/hydratk/lib/database/__init__.py
src/hydratk/lib/database/dbo/__init__.py
src/hydratk/lib/database/dbo/drivers/__init__.py
src/hydratk/lib/database/dbo/drivers/mssql/__init__.py
src/hydratk/lib/database/dbo/drivers/mssql/driver.py
src/hydratk/lib/database/dbo/drivers/mysql/__init__.py
src/hydratk_lib_network.egg-info/PKG-INFO
src/hydratk_lib_network.egg-info/SOURCES.txt
src/hydratk_lib_network.egg-info/dependency_links.txt
src/hydratk_lib_network.egg-info/not-zip-safe
src/hydratk_lib_network.egg-info/top_level.txt
