Metadata-Version: 1.1
Name: hydratk-lib-network
Version: 0.2.2
Summary: Clients/API for many network protocols and technologies
Home-page: http://libraries.hydratk.org/network
Author: Petr Rašek, HydraTK team
Author-email: bowman@hydratk.org, team@hydratk.org
License: BSD
Keywords: hydratk,database,soap,rest,jms,java,gui
Platform: Linux
Platform: FreeBSD
Classifier: Development Status :: 5 - Production/Stable
Classifier: Environment :: Console
Classifier: Environment :: Other Environment
Classifier: Intended Audience :: Developers
Classifier: License :: Freely Distributable
Classifier: Operating System :: OS Independent
Classifier: License :: OSI Approved :: BSD License
Classifier: Programming Language :: Python
Classifier: Programming Language :: Python :: 2.6
Classifier: Programming Language :: Python :: 2.7
Classifier: Programming Language :: Python :: 3.3
Classifier: Programming Language :: Python :: 3.4
Classifier: Programming Language :: Python :: 3.5
Classifier: Programming Language :: Python :: 3.6
Classifier: Programming Language :: Python :: Implementation
Classifier: Programming Language :: Python :: Implementation :: CPython
Classifier: Programming Language :: Python :: Implementation :: PyPy
Classifier: Topic :: Software Development :: Libraries :: Application Frameworks
Classifier: Topic :: Utilities
